hdroller/__init__.py
hdroller/collections.py
hdroller/eval_pool.py
hdroller/math.py
hdroller/pool.py
hdroller/tournament.py
hdroller/die/__init__.py
hdroller/die/base.py
hdroller/die/create.py
hdroller/die/empty.py
hdroller/die/func.py
hdroller/die/scalar.py
hdroller/die/vector.py
hdroller-0.6.7.dist-info/LICENSE.md
hdroller-0.6.7.dist-info/METADATA
hdroller-0.6.7.dist-info/WHEEL
hdroller-0.6.7.dist-info/top_level.txt
hdroller-0.6.7.dist-info/RECORD
