Metadata-Version: 2.1
Name: hdroller
Version: 0.6.7
Summary: A package for computing dice probabilities
Home-page: https://gitlab.com/highdiceroller/hdroller
Author: Albert Julius Liu
Author-email: ajul1987+highdiceroller@gmail.com
License: UNKNOWN
Project-URL: Twitter, https://twitter.com/highdiceroller
Platform: UNKNOWN
Classifier: Development Status :: 3 - Alpha
Classifier: License :: OSI Approved :: MIT License
Classifier: Programming Language :: Python :: 3
Classifier: Topic :: Games/Entertainment :: Role-Playing
Classifier: Topic :: Scientific/Engineering :: Mathematics
Requires-Python: >=3.9
License-File: LICENSE.md
